ardexa_black_box.py
ardexa_black_box-1.5.1.dist-info/DESCRIPTION.rst
ardexa_black_box-1.5.1.dist-info/METADATA
ardexa_black_box-1.5.1.dist-info/RECORD
ardexa_black_box-1.5.1.dist-info/WHEEL
ardexa_black_box-1.5.1.dist-info/entry_points.txt
ardexa_black_box-1.5.1.dist-info/metadata.json
ardexa_black_box-1.5.1.dist-info/top_level.txt
