Metadata-Version: 2.0
Name: ardexa-black-box
Version: 1.5.1
Summary: Regularly check key Linux health items and report to a log file
Home-page: UNKNOWN
Author: Ardexa Pty Limited
Author-email: support@ardexa.com
License: UNKNOWN
Keywords: ardexa
Platform: UNKNOWN
Classifier: License :: OSI Approved :: MIT License
Classifier: Programming Language :: Python :: 2
Classifier: Programming Language :: Python :: 2.7
Classifier: Programming Language :: Python :: 3
Classifier: Programming Language :: Python :: 3.4
Classifier: Programming Language :: Python :: 3.5
Classifier: Programming Language :: Python :: 3.6
Requires-Python: >=2.7
Requires-Dist: dnspython
Requires-Dist: future
Requires-Dist: psutil
Requires-Dist: requests
